{
  "name": "Oscar Webster",
  "age": 18,
  "address": {
    "street": "Ziwoj Park",
    "city": "Hiltidbog",
    "state": "ND",
    "zip": "57198"
  },
  "contact": {
    "phone": "(247) 345-5363",
    "servicePhone": "800637156"
  },
  "birthday": "1963-06-21T20:40:00.442Z",
  "ip": "55.192.40.4",
  "foo": "bar",
  "profile": {
    "about": "Game uroz wo iluk duwe obebeap ugauke zogil heij gate aho kullu ezigu piffamza weiva butap. Zolom wabmubu huvzel fiznoifi iz deagduj hebmadwi capa potu nat ko mi vokimojuh zumseram cehig. Simki ezi pe adopebi gif gildujvi nitpuzih jiw vi korvi fus nanahfa. Wuz habzises mipte gezmejvo wucjal vek kizunduz biruur mebfav be heh nekki ji mah mi usifoza. Senujic boku no se cir najiw azginse pije gusag funu donureh macgefuja cas gur fuune orzanug. Ib zowrewne lotwa zajgahvi nismak wapuwedi apo udlo to wubafi ajuadwi pegnac zewarju kuhica. Nat pij enrukotu kirbajgo kodpuavo sioliji wum af gihode remzu lu gat pog pe dub wor uzobo.",
    "bio": "Jus erizeser ke balfepusu wi sak nagouk lobni zislo uvmaole siwroh peksube dura jijnog pisco mehudlim. Bod omotub bocomohi upelug lir aza keh kug luvfulmo fojewe ukaad ok si fole rile ceb pe egorar. Imimocos akdenzor nelza puwfitu ezsomi ageeki fu ceh des rid gu wersobu egguk cali ib re zuviffi gokgazzi. Weegole enefemop vuzij sudib ga upalula cu sifjakil zihej suhi menocof ufudi nuodura."
  },
  "apiKey": "95477f96959762b77fab83231562cd87ec618187144ec1383d3cb19091d8995e",
  "currency": {
    "code": "SDG",
    "name": "Sudan Pound"
  }
}